storybuilder/__init__.py
storybuilder/builders/__init__.py
storybuilder/builders/emotion_analyzer.py
storybuilder/builders/emotion_mapper.py
storybuilder/builders/facial_emotion.py
storybuilder/builders/posture_selector.py
storybuilder/builders/sentiment_description.py
storybuilder/builders/story.py
storybuilder/builders/pages/__init__.py
storybuilder/builders/pages/mixins.py
storybuilder/builders/pages/page.py
storybuilder/builders/pages/scenario.py
storybuilder/config/__init__.py
storybuilder/config/figures.py
storybuilder/config/profiles.py
storybuilder/core/__init__.py
storybuilder/core/mhtml.py
storybuilder/core/mlist.py
storybuilder/core/mtext.py
storybuilder/models/__init__.py
storybuilder/models/actor.py
storybuilder/models/actor_manager.py
storybuilder/models/board.py
storybuilder/models/content.py
storybuilder/models/interaction.py
storybuilder/models/scene.py
storybuilder/models/script.py
storybuilder/services/__init__.py
storybuilder/services/cos.py
storybuilder/services/speech.py
storybuilder/services/voice.py
storybuilder/utils/__init__.py
storybuilder/utils/constants.py
storybuilder/utils/helpers.py
storybuilder/utils/notebook_utils.py
storybuilder-0.1.7.dist-info/licenses/LICENSE
storybuilder-0.1.7.dist-info/METADATA
storybuilder-0.1.7.dist-info/WHEEL
storybuilder-0.1.7.dist-info/top_level.txt
storybuilder-0.1.7.dist-info/RECORD
